cacheproperty/__init__.py
cacheproperty/base.py
cacheproperty-0.1.1.dist-info/DESCRIPTION.rst
cacheproperty-0.1.1.dist-info/METADATA
cacheproperty-0.1.1.dist-info/RECORD
cacheproperty-0.1.1.dist-info/WHEEL
cacheproperty-0.1.1.dist-info/entry_points.txt
cacheproperty-0.1.1.dist-info/metadata.json
cacheproperty-0.1.1.dist-info/top_level.txt
