Metadata-Version: 2.0
Name: cacheproperty
Version: 0.1.1
Summary: A subclass of python's builtin property class that removes boilerplate by implementing the h_hidden_attribute pattern with a single decorator call. Also afacilitates invalidation of the cached hidden attribute with a @cacheproperty.invalidate decorator on any other methods or properties in a class.
Home-page: https://github.com/mattHawthorn/cacheproperty
Author: Matthew Hawthorn
Author-email: hawthorn.matthew@gmail.com
License: GNU General Public License v3
Keywords: cacheproperty
Platform: UNKNOWN
Classifier: Development Status :: 2 - Pre-Alpha
Classifier: Intended Audience :: Developers
Classifier: License :: OSI Approved :: GNU General Public License v3 (GPLv3)
Classifier: Natural Language :: English
Classifier: Topic :: Utilities
Classifier: Programming Language :: Python :: 3
Classifier: Programming Language :: Python :: 3.4
Classifier: Programming Language :: Python :: 3.5
Classifier: Programming Language :: Python :: 3.6
